cplex-22.1.1.1.data/purelib/cplex/__init__.py
cplex-22.1.1.1.data/purelib/cplex/aborter.py
cplex-22.1.1.1.data/purelib/cplex/callbacks.py
cplex-22.1.1.1.data/purelib/cplex/constant_class.py
cplex-22.1.1.1.data/purelib/cplex/model_info.py
cplex-22.1.1.1.data/purelib/cplex/paramset.py
cplex-22.1.1.1.data/purelib/cplex/_internal/__init__.py
cplex-22.1.1.1.data/purelib/cplex/_internal/_anno.py
cplex-22.1.1.1.data/purelib/cplex/_internal/_aux_functions.py
cplex-22.1.1.1.data/purelib/cplex/_internal/_baseinterface.py
cplex-22.1.1.1.data/purelib/cplex/_internal/_callbackinfoenum.py
cplex-22.1.1.1.data/purelib/cplex/_internal/_constants.py
cplex-22.1.1.1.data/purelib/cplex/_internal/_constantsenum.py
cplex-22.1.1.1.data/purelib/cplex/_internal/_list_array_utils.py
cplex-22.1.1.1.data/purelib/cplex/_internal/_matrices.py
cplex-22.1.1.1.data/purelib/cplex/_internal/_multiobj.py
cplex-22.1.1.1.data/purelib/cplex/_internal/_multiobjsoln.py
cplex-22.1.1.1.data/purelib/cplex/_internal/_ostream.py
cplex-22.1.1.1.data/purelib/cplex/_internal/_parameter_classes.py
cplex-22.1.1.1.data/purelib/cplex/_internal/_parameter_hierarchy.py
cplex-22.1.1.1.data/purelib/cplex/_internal/_parameters_auto.py
cplex-22.1.1.1.data/purelib/cplex/_internal/_procedural.py
cplex-22.1.1.1.data/purelib/cplex/_internal/_pwl.py
cplex-22.1.1.1.data/purelib/cplex/_internal/_pycplex.py
cplex-22.1.1.1.data/purelib/cplex/_internal/_pycplex_platform.py
cplex-22.1.1.1.data/purelib/cplex/_internal/_solutionstrategyenum.py
cplex-22.1.1.1.data/purelib/cplex/_internal/_subinterfaces.py
cplex-22.1.1.1.data/purelib/cplex/_internal/libcplex2211.so
cplex-22.1.1.1.data/purelib/cplex/_internal/py311_cplex2211.so
cplex-22.1.1.1.data/purelib/cplex/exceptions/__init__.py
cplex-22.1.1.1.data/purelib/cplex/exceptions/error_codes.py
cplex-22.1.1.1.data/purelib/cplex/exceptions/errors.py
cplex-22.1.1.1.data/scripts/cpoptimizer
cplex-22.1.1.1.data/scripts/cpxchecklic
cplex-22.1.1.1.data/scripts/libcplex2211.so
cplex-22.1.1.1.dist-info/LI_en.txt
cplex-22.1.1.1.dist-info/METADATA
cplex-22.1.1.1.dist-info/WHEEL
cplex-22.1.1.1.dist-info/RECORD
