Metadata-Version: 2.1
Name: cplex
Version: 22.1.1.1
Summary: A Python interface to the CPLEX Callable Library, Community Edition.
Home-page: https://www.ibm.com/analytics/data-science/prescriptive-analytics/cplex-optimizer/
Author: IBM
Author-email: UNKNOWN
License: Proprietary
Platform: UNKNOWN
